aurdrobotsd/__init__.py
aurdrobotsd/arduino.py
aurdrobotsd-9.0.0.dist-info/METADATA
aurdrobotsd-9.0.0.dist-info/WHEEL
aurdrobotsd-9.0.0.dist-info/top_level.txt
aurdrobotsd-9.0.0.dist-info/RECORD
