Metadata-Version: 2.1
Name: aurdrobotsd
Version: 9.0.0
Summary: its project for Aurdino but It for Python
Home-page: https://github.com/alikushbaev/Arduino
Author: __init__
Author-email: jamshidkushbaev@gmail.com
Project-URL: Documentation, https://github.com/alikushbaev/Arduino
Classifier: Programming Language :: Python :: 3
Classifier: License :: OSI Approved :: MIT License
Classifier: Operating System :: OS Independent
Requires-Python: >=3.11
Requires-Dist: pyserial
